viz_image_deobfuscate/__init__.py
viz_image_deobfuscate/cli.py
viz_image_deobfuscate/deobfuscate.py
viz_image_deobfuscate-0.1.4.dist-info/entry_points.txt
viz_image_deobfuscate-0.1.4.dist-info/LICENSE
viz_image_deobfuscate-0.1.4.dist-info/WHEEL
viz_image_deobfuscate-0.1.4.dist-info/METADATA
viz_image_deobfuscate-0.1.4.dist-info/RECORD
