Metadata-Version: 2.1
Name: viz-image-deobfuscate
Version: 0.1.4
Summary: Deobfuscate Viz-style manga images.
Home-page: https://github.com/minormending/viz-image-deobfuscate
License: MIT
Keywords: viz,manga,deobfuscate,image
Author: Kevin Ramdath
Author-email: krpent@gmail.com
Requires-Python: >=3.10,<4.0
Classifier: License :: OSI Approved :: MIT License
Classifier: Programming Language :: Python :: 3
Classifier: Programming Language :: Python :: 3.10
Requires-Dist: Pillow (>=9.1.0,<10.0.0)
Requires-Dist: piexif (>=1.1.3,<2.0.0)
Project-URL: Repository, https://github.com/minormending/viz-image-deobfuscate
